sosin/__init__.py
sosin/databases/db.py
sosin/databases/rdb/maria.py
sosin/databases/rdb/postgre.py
sosin/rpa/email_mgr.py
sosin/rpa/sms_mgr.py
sosin/utils/currency.py
sosin/utils/history.py
sosin/utils/log.py
sosin/utils/progress.py
sosin/utils/secret.py
sosin/utils/zip.py
sosin/web/content.py
sosin/web/cookie.py
sosin/web/session.py
sosin/web/session_async.py
sosin/web/translate.py
sosin/web/virtual.py
sosin-1.5.3.dist-info/LICENSE
sosin-1.5.3.dist-info/METADATA
sosin-1.5.3.dist-info/WHEEL
sosin-1.5.3.dist-info/top_level.txt
sosin-1.5.3.dist-info/RECORD
