Metadata-Version: 2.1
Name: sosin
Version: 1.5.3
Summary: Python utils for general works
Home-page: https://github.com/devsosin/sosin
Author: Jason Choi
Author-email: sosincomp@gmail.com
License: MIT
Classifier: Programming Language :: Python :: 3
Classifier: License :: OSI Approved :: MIT License
Classifier: Operating System :: OS Independent
Requires-Python: >=3.9
License-File: LICENSE
Requires-Dist: requests
Requires-Dist: requests-toolbelt
Requires-Dist: httpx
